[
  {
    "name": "云上舞白",
    "hex": "#F0EFEB",
    "year": "2026",
    "rgb": "240,239,235"
  },
  {
    "name": "泡菜绿",
    "hex": "#4E6813",
    "year": "2025",
    "rgb": "78,104,19",
    "type": "绿色"
  },
  {
    "name": "光环靛蓝",
    "hex": "#B0A6DF",
    "year": "2025",
    "rgb": "176,166,223",
    "type": "蓝色"
  },
  {
    "name": "奶油黄",
    "hex": "#FFEDA8",
    "year": "2025",
    "rgb": "255,237,168",
    "type": "黄色"
  },
  {
    "name": "阿尔卑斯燕麦色",
    "hex": "#F0E7DA",
    "year": "2025",
    "rgb": "240,231,218"
  },
  {
    "name": "樱桃红",
    "hex": "#74070E",
    "year": "2025",
    "rgb": "116,7,14",
    "type": "红色"
  },
  {
    "name": "柔和桃",
    "hex": "#FFBE98",
    "rgb": "255,190,152",
    "year": "2024"
  },
  {
    "name": "非凡洋红",
    "hex": "#BE3455",
    "rgb": "190,52,85",
    "year": "2023",
    "type": "红色"
  },
  {
    "name": "长春花蓝",
    "hex": "#6667AB",
    "rgb": "102,103,171",
    "year": "2022",
    "type": "蓝色"
  },
  {
    "name": "明亮黄",
    "hex": "#F5DF4D",
    "rgb": "245,223,77",
    "year": "2021",
    "type": "黄色"
  },
  {
    "name": "极致灰",
    "hex": "#939597",
    "rgb": "147,149,151",
    "year": "2021"
  },
  {
    "name": "经典蓝",
    "hex": "#0F4C81",
    "rgb": "15,76,129",
    "year": "2020",
    "type": "蓝色"
  },
  {
    "name": "珊瑚橙",
    "hex": "#FF6F61",
    "rgb": "255,111,97",
    "year": "2019"
  },
  {
    "name": "紫外光",
    "hex": "#5F4B8B",
    "rgb": "95,75,139",
    "year": "2018",
    "type": "紫色"
  },
  {
    "name": "草木绿",
    "hex": "#88B04B",
    "rgb": "136,176,75",
    "year": "2017",
    "type": "绿色"
  },
  {
    "name": "水晶粉",
    "hex": "#F7CAC9",
    "rgb": "247,202,201",
    "year": "2016",
    "type": "粉色"
  },

  {
    "name": "宁静蓝",
    "hex": "#92A8D1",
    "rgb": "146,168,209",
    "year": "2016",
    "type": "蓝色"
  },
  {
    "name": "玛萨拉酒红",
    "hex": "#955251",
    "rgb": "149,82,81",
    "year": "2015",
    "type": "红色"
  },
  {
    "name": "璀璨紫兰花",
    "hex": "#B565A7",
    "rgb": "181,101,167",
    "year": "2014",
    "type": "紫色"
  },
  {
    "name": "翡翠绿",
    "hex": "#009B77",
    "rgb": "0,155,119",
    "year": "2013",
    "type": "绿色"
  },
  {
    "name": "探戈橘",
    "hex": "#E2492F",
    "rgb": "226,73,47",
    "year": "2012",
    "type": "红色"
  },
  {
    "name": "忍冬红",
    "hex": "#CB6586",
    "rgb": "203,101,134",
    "year": "2011",
    "type": "红色"
  },
  {
    "name": "松石绿",
    "hex": "#45B5AA",
    "rgb": "69,181,170",
    "year": "2010",
    "type": "绿色"
  },
  {
    "name": "含羞草黄",
    "hex": "#F0C05A",
    "rgb": "240,192,90",
    "year": "2009",
    "type": "黄色"
  },
  {
    "name": "鸢尾蓝",
    "hex": "#5A5B9F",
    "rgb": "90,91,159",
    "year": "2008",
    "type": "蓝色"
  },
  {
    "name": "辣椒红",
    "hex": "#9B1B30",
    "rgb": "155,27,48",
    "year": "2007",
    "type": "红色"
  },
  {
    "name": "沙色金",
    "hex": "#DECDBE",
    "rgb": "222,205,190",
    "year": "2006"
  },
  {
    "name": "虎皮百合",
    "hex": "#53B0AE",
    "rgb": "83,176,174",
    "year": "2005"
  },
  {
    "name": "蓝色绿松石",
    "hex": "#E2583E",
    "rgb": "226,88,62",
    "year": "2004"
  },
  {
    "name": "水色天空",
    "hex": "#7BC4C4",
    "rgb": "123,196,196",
    "year": "2003",
    "type": "青色"
  },
  {
    "name": "真实红",
    "hex": "#BF1932",
    "rgb": "191,25,50",
    "year": "2002",
    "type": "红色"
  },

  {
    "name": "桃色玫瑰色",
    "hex": "#C74375",
    "rgb": "199,67,117",
    "year": "2001",
    "type": "红色"
  },

  {
    "name": "蔚蓝",
    "hex": "#98B2D1",
    "rgb": "152,178,209",
    "year": "2000",
    "type": "蓝色"
  }
]
